boyermoore/__init__.py
boyermoore-1.0.0.dist-info/LICENSE
boyermoore-1.0.0.dist-info/METADATA
boyermoore-1.0.0.dist-info/WHEEL
boyermoore-1.0.0.dist-info/top_level.txt
boyermoore-1.0.0.dist-info/RECORD
