Metadata-Version: 2.1
Name: boyermoore
Version: 1.0.0
Summary: Boyer-moore in pure python, search for unicode strings in large files very quickly
Home-page: http://github.com/eriknyquist/boyermoore
Author: Erik Nyquist
Author-email: eknyquist@gmail.com
License: Apache 2.0
Project-URL: Documentation, https://eriknyquist.github.io/boyermoore
Project-URL: Issues, https://github.com/eriknyquist/boyermoore/issues
Project-URL: Contributions, https://eriknyquist.github.io/boyermoore/#contributions
Keywords: boyermoore,boyer-moore,search,filesearch,fastsearch,boyermorehorspool,boyer-moore-horspool
Platform: UNKNOWN
Classifier: Development Status :: 5 - Production/Stable
Classifier: Intended Audience :: Developers
Classifier: Intended Audience :: Science/Research
Classifier: Intended Audience :: Education
Classifier: Intended Audience :: Information Technology
Classifier: License :: OSI Approved :: Apache Software License
Classifier: Programming Language :: Python :: 3
Classifier: Programming Language :: Python :: 3.7
Classifier: Programming Language :: Python :: 3.8
Classifier: Programming Language :: Python :: 3.9
Classifier: Programming Language :: Python :: 3.10
Requires-Python: >=3.7
